ex5/ex5.v
`timescale 1ps/1ps
module led(input clk, st, input [4:0]mem[0:31], output [4:0] dot);
    logic [4:0] dot=5'b0;
    logic [4:0] cnt=0;
    logic en = 0;
    always@(posedge clk) begin 
        if(st)if(en ==0) en <=1;
        if(en) begin
            dot <= mem[cnt];
            $display("%b", mem[cnt]);
            $display("%b", dot);
            cnt <= cnt+1;
            if(cnt==31) begin
                cnt<=0;
                dot <= 5'b0;
                en<=0;
            end
        end
    end
endmodule



module test;
    logic [4:0]mem[0:31];
    logic [4:0] dot;
    logic st=1'b0;
    bit clk;

    integer i;
    always #5 clk = ~clk;
    led x(clk, st, mem, dot);
    initial begin
        $readmemb("pattern.txt", mem);
        for(i=0;i<32;i++)$display("%b", mem[i]);
        $dumpfile("led.vcd");
        $dumpvars(0, test);
        #100;
        st=1;
        #10;
        st=0;
        #500;
        $finish;
    end
endmodule

ex5/led.vcd
$date
	Sat May 30 12:29:09 2020
$end
$version
	Icarus Verilog
$end
$timescale
	1ps
$end
$scope module test $end
$var wire 5 ! dot [4:0] $end
$var reg 1 " st $end
$var reg 1 # clk $end
$var integer 32 $ i [31:0] $end
$scope module x $end
$var wire 1 # clk $end
$var wire 1 " st $end
$var reg 5 % cnt [4:0] $end
$var reg 5 & dot [4:0] $end
$var reg 1 ' en $end
$upscope $end
$upscope $end
$enddefinitions $end
#0
$dumpvars
0'
b0 &
b0 %
b100000 $
0#
0"
b0 !
$end
#5
1#
#10
0#
#15
1#
#20
0#
#25
1#
#30
0#
#35
1#
#40
0#
#45
1#
#50
0#
#55
1#
#60
0#
#65
1#
#70
0#
#75
1#
#80
0#
#85
1#
#90
0#
#95
1#
#100
0#
1"
#105
1'
1#
#110
0#
0"
#115
b1 %
1#
#120
0#
#125
b10 %
b11110 !
b11110 &
1#
#130
0#
#135
b11 %
b1 !
b1 &
1#
#140
0#
#145
b100 %
b11110 !
b11110 &
1#
#150
0#
#155
b101 %
b0 !
b0 &
1#
#160
0#
#165
b110 %
b11111 !
b11111 &
1#
#170
0#
#175
b111 %
b10101 !
b10101 &
1#
#180
0#
#185
b1000 %
1#
#190
0#
#195
b1001 %
b0 !
b0 &
1#
#200
0#
#205
b1010 %
b11111 !
b11111 &
1#
#210
0#
#215
b1011 %
b10100 !
b10100 &
1#
#220
0#
#225
b1100 %
b11011 !
b11011 &
1#
#230
0#
#235
b1101 %
b0 !
b0 &
1#
#240
0#
#245
b1110 %
b11111 !
b11111 &
1#
#250
0#
#255
b1111 %
b0 !
b0 &
1#
#260
0#
#265
b10000 %
b11111 !
b11111 &
1#
#270
0#
#275
b10001 %
b1 !
b1 &
1#
#280
0#
#285
b10010 %
1#
#290
0#
#295
b10011 %
b0 !
b0 &
1#
#300
0#
#305
b10100 %
b11111 !
b11111 &
1#
#310
0#
#315
b10101 %
b10001 !
b10001 &
1#
#320
0#
#325
b10110 %
b11111 !
b11111 &
1#
#330
0#
#335
b10111 %
b0 !
b0 &
1#
#340
0#
#345
b11000 %
b11111 !
b11111 &
1#
#350
0#
#355
b11001 %
b10001 !
b10001 &
1#
#360
0#
#365
b11010 %
b10111 !
b10111 &
1#
#370
0#
#375
b11011 %
b0 !
b0 &
1#
#380
0#
#385
b11100 %
b11101 !
b11101 &
1#
#390
0#
#395
b11101 %
b0 !
b0 &
1#
#400
0#
#405
b11110 %
b11101 !
b11101 &
1#
#410
0#
#415
b11111 %
b0 !
b0 &
1#
#420
0#
#425
0'
b0 %
b0 !
b0 &
1#
