ex5/ex5.v
`timescale 1ps/1ps
module led(input clk, st, input [4:0] mem [0:31], output [4:0] dot);
    logic [4:0] dot= 0;
    logic [4:0] cnt= 0;
    logic en = 0;
    always@(posedge clk) begin 
        if(en) begin
            dot <= mem[cnt];
            cnt <= cnt+1;
            if(cnt==31) begin
                en<=0;
            end
        end else dot<=0;
        if(st) en<=1;
    end
endmodule

module test;
    logic [4:0]mem[0:31];
    logic [4:0] dot;
    logic st=1'b0;
    bit clk;

    integer i;
    always #5 clk = ~clk;
    led x(clk, st, mem, dot);
    initial begin
        $readmemb("pattern.txt", mem);
        $dumpfile("led.vcd");
        $dumpvars(0, test);
        #30;
        st=1;
        #10;
        st=0;
        #340;
        st=1;
        #10;
        st=0;
        #360;
        $finish;
    end
endmodule

ex5/led.vcd
$date
	Sat May 30 16:18:54 2020
$end
$version
	Icarus Verilog
$end
$timescale
	1ps
$end
$scope module test $end
$var wire 5 ! dot [4:0] $end
$var reg 1 " st $end
$var reg 1 # clk $end
$scope module x $end
$var wire 1 # clk $end
$var wire 1 " st $end
$var reg 5 $ cnt [4:0] $end
$var reg 5 % dot [4:0] $end
$var reg 1 & en $end
$upscope $end
$upscope $end
$enddefinitions $end
#0
$dumpvars
0&
b0 %
b0 $
0#
0"
b0 !
$end
#5
1#
#10
0#
#15
1#
#20
0#
#25
1#
#30
0#
1"
#35
1&
1#
#40
0#
0"
#45
b1 $
1#
#50
0#
#55
b10 $
b11110 !
b11110 %
1#
#60
0#
#65
b11 $
b1 !
b1 %
1#
#70
0#
#75
b100 $
b11110 !
b11110 %
1#
#80
0#
#85
b101 $
b0 !
b0 %
1#
#90
0#
#95
b110 $
b11111 !
b11111 %
1#
#100
0#
#105
b111 $
b10101 !
b10101 %
1#
#110
0#
#115
b1000 $
1#
#120
0#
#125
b1001 $
b0 !
b0 %
1#
#130
0#
#135
b1010 $
b11111 !
b11111 %
1#
#140
0#
#145
b1011 $
b10100 !
b10100 %
1#
#150
0#
#155
b1100 $
b11011 !
b11011 %
1#
#160
0#
#165
b1101 $
b0 !
b0 %
1#
#170
0#
#175
b1110 $
b11111 !
b11111 %
1#
#180
0#
#185
b1111 $
b0 !
b0 %
1#
#190
0#
#195
b10000 $
b11111 !
b11111 %
1#
#200
0#
#205
b10001 $
b1 !
b1 %
1#
#210
0#
#215
b10010 $
1#
#220
0#
#225
b10011 $
b0 !
b0 %
1#
#230
0#
#235
b10100 $
b11111 !
b11111 %
1#
#240
0#
#245
b10101 $
b10001 !
b10001 %
1#
#250
0#
#255
b10110 $
b11111 !
b11111 %
1#
#260
0#
#265
b10111 $
b0 !
b0 %
1#
#270
0#
#275
b11000 $
b11111 !
b11111 %
1#
#280
0#
#285
b11001 $
b10001 !
b10001 %
1#
#290
0#
#295
b11010 $
b10111 !
b10111 %
1#
#300
0#
#305
b11011 $
b0 !
b0 %
1#
#310
0#
#315
b11100 $
b11101 !
b11101 %
1#
#320
0#
#325
b11101 $
b0 !
b0 %
1#
#330
0#
#335
b11110 $
b11101 !
b11101 %
1#
#340
0#
#345
b11111 $
b0 !
b0 %
1#
#350
0#
#355
0&
b0 $
b11101 !
b11101 %
1#
#360
0#
#365
b0 !
b0 %
1#
#370
0#
#375
1#
#380
0#
1"
#385
1&
1#
#390
0#
0"
#395
b1 $
1#
#400
0#
#405
b10 $
b11110 !
b11110 %
1#
#410
0#
#415
b11 $
b1 !
b1 %
1#
#420
0#
#425
b100 $
b11110 !
b11110 %
1#
#430
0#
#435
b101 $
b0 !
b0 %
1#
#440
0#
#445
b110 $
b11111 !
b11111 %
1#
#450
0#
#455
b111 $
b10101 !
b10101 %
1#
#460
0#
#465
b1000 $
1#
#470
0#
#475
b1001 $
b0 !
b0 %
1#
#480
0#
#485
b1010 $
b11111 !
b11111 %
1#
#490
0#
#495
b1011 $
b10100 !
b10100 %
1#
#500
0#
#505
b1100 $
b11011 !
b11011 %
1#
#510
0#
#515
b1101 $
b0 !
b0 %
1#
#520
0#
#525
b1110 $
b11111 !
b11111 %
1#
#530
0#
#535
b1111 $
b0 !
b0 %
1#
#540
0#
#545
b10000 $
b11111 !
b11111 %
1#
#550
0#
#555
b10001 $
b1 !
b1 %
1#
#560
0#
#565
b10010 $
1#
#570
0#
#575
b10011 $
b0 !
b0 %
1#
#580
0#
#585
b10100 $
b11111 !
b11111 %
1#
#590
0#
#595
b10101 $
b10001 !
b10001 %
1#
#600
0#
#605
b10110 $
b11111 !
b11111 %
1#
#610
0#
#615
b10111 $
b0 !
b0 %
1#
#620
0#
#625
b11000 $
b11111 !
b11111 %
1#
#630
0#
#635
b11001 $
b10001 !
b10001 %
1#
#640
0#
#645
b11010 $
b10111 !
b10111 %
1#
#650
0#
#655
b11011 $
b0 !
b0 %
1#
#660
0#
#665
b11100 $
b11101 !
b11101 %
1#
#670
0#
#675
b11101 $
b0 !
b0 %
1#
#680
0#
#685
b11110 $
b11101 !
b11101 %
1#
#690
0#
#695
b11111 $
b0 !
b0 %
1#
#700
0#
#705
0&
b0 $
b11101 !
b11101 %
1#
#710
0#
#715
b0 !
b0 %
1#
