ex7/fibo/imem.v
module imem(input [5:0] pc, output logic [9:0] o);
	always_comb
		case(pc)
		// synopsys full_case parallel_case
		5'h00: o = 10'b0_10_000_00_01; // r2 <- r0 (b) + r1 (a)
		5'h01: o = 10'b0_00_001_00_01; // r0 <- r1
		5'h02: o = 10'b0_01_001_00_10; // r1 <- r2
		5'h03: o = 10'b0_10_000_00_01; // r2 <- r0 (b) + r1 (a)
		5'h04: o = 10'b0_00_001_00_01; // r0 <- r1
		5'h05: o = 10'b0_01_001_00_10; // r1 <- r2
		5'h06: o = 10'b0_10_000_00_01; // r2 <- r0 (b) + r1 (a)
		5'h07: o = 10'b0_00_001_00_01; // r0 <- r1
		5'h08: o = 10'b0_01_001_00_10; // r1 <- r2
		5'h09: o = 10'b0_10_000_00_01; // r2 <- r0 (b) + r1 (a)
		5'h0a: o = 10'b0_00_001_00_01; // r0 <- r1
		5'h0b: o = 10'b0_01_001_00_10; // r1 <- r2
		5'h0c: o = 10'b0_10_000_00_01; // r2 <- r0 (b) + r1 (a)
		5'h0d: o = 10'b0_00_001_00_01; // r0 <- r1
		5'h0e: o = 10'b0_01_001_00_10; // r1 <- r2
		5'h0f: o = 10'b0_10_000_00_01; // r2 <- r0 (b) + r1 (a)
		5'h10: o = 10'b0_00_001_00_01; // r0 <- r1
		5'h11: o = 10'b0_01_001_00_10; // r1 <- r2
		5'h12: o = 10'b0_10_000_00_01; // r2 <- r0 (b) + r1 (a)
		5'h13: o = 10'b0_00_001_00_01; // r0 <- r1
		5'h14: o = 10'b0_01_001_00_10; // r1 <- r2
		5'h15: o = 11'b1_00_000_00_00; // halt
		endcase
endmodule

ex7/fibo/pc.v
module pc(input halt, output logic [5:0] pc, input clk, rst);
	always @(posedge clk or posedge rst)
		if(rst) pc <= 0;
		else if(!halt) pc <= pc + 1;
endmodule

ex7/fibo/alu.v
module alu(input [15:0] a, b, input [2:0] op, output logic [15:0] r);
	enum {ADD, TRU} OPTYPE;
	always_comb
		case(op[0])
		// synopsys full_case parallel_case
		ADD: r = a+b;	
		TRU: r = a;
		endcase
endmodule

ex7/fibo/rega.v
module rega(input logic [1:0] arad, brad, output logic [15:0] a, b,
	input we, input logic [1:0] wad, input [15:0] wd,
	input clk, rst);
	logic [15:0] regar [3:0];
	always @(posedge clk or posedge rst) begin
		if(rst) begin
			regar[0] <= 0;
			regar[1] <= 1;
		end else if(we) regar[wad] <= wd;
	end
	assign a = regar[arad];
	assign b = regar[brad];
endmodule

ex7/fibo/top.v
module top(input clk, rst);
	logic [15:0] a, b, wd;
	logic [1:0] arad, brad, wad;
	logic [2:0] op;
	logic [5:0] pca;
	logic [9:0] o;
	rega rega(arad, brad, a, b, we, wad, wd, clk, rst);
	alu alu(a, b, op, wd);
	pc pc(h, pca, clk, rst);
	imem imem(pca, o);
	assign {h, wad, op, brad, arad} = o;
	assign we = ~h;
endmodule

ex7/test.v
module test;
	logic clk, rst;
	top top(clk, rst);
	always #5 clk =~ clk;
	initial begin
	$dumpfile("fibo.vcd");
	$dumpvars(0, top);
	rst = 1;
	clk = 0;
	#20
	rst = 0;
	#500
	$finish;
	end
endmodule

ex7/fibo/fibo.vcd
$date
	Fri May 29 03:55:31 2020
$end
$version
	Icarus Verilog
$end
$timescale
	1s
$end
$scope module test $end
$scope module top $end
$var wire 1 ! clk $end
$var wire 1 " rst $end
$var wire 1 # we $end
$var wire 16 $ wd [15:0] $end
$var wire 2 % wad [1:0] $end
$var wire 6 & pca [5:0] $end
$var wire 3 ' op [2:0] $end
$var wire 10 ( o [9:0] $end
$var wire 1 ) h $end
$var wire 2 * brad [1:0] $end
$var wire 16 + b [15:0] $end
$var wire 2 , arad [1:0] $end
$var wire 16 - a [15:0] $end
$scope module alu $end
$var wire 3 . op [2:0] $end
$var wire 16 / b [15:0] $end
$var wire 16 0 a [15:0] $end
$var reg 16 1 r [15:0] $end
$upscope $end
$scope module imem $end
$var wire 6 2 pc [5:0] $end
$var reg 10 3 o [9:0] $end
$upscope $end
$scope module pc $end
$var wire 1 ! clk $end
$var wire 1 ) halt $end
$var wire 1 " rst $end
$var reg 6 4 pc [5:0] $end
$upscope $end
$scope module rega $end
$var wire 16 5 a [15:0] $end
$var wire 2 6 arad [1:0] $end
$var wire 16 7 b [15:0] $end
$var wire 2 8 brad [1:0] $end
$var wire 1 ! clk $end
$var wire 1 " rst $end
$var wire 2 9 wad [1:0] $end
$var wire 16 : wd [15:0] $end
$var wire 1 # we $end
$upscope $end
$upscope $end
$upscope $end
$enddefinitions $end
#0
$dumpvars
b1 :
b10 9
b0 8
b0 7
b1 6
b1 5
b0 4
b100000001 3
b0 2
b1 1
b1 0
b0 /
b0 .
b1 -
b1 ,
b0 +
b0 *
0)
b100000001 (
b0 '
b0 &
b10 %
b1 $
1#
1"
0!
$end
#5
1!
#10
0!
#15
1!
#20
0!
0"
#25
b0 %
b0 9
b1 '
b1 .
b10001 (
b10001 3
b1 &
b1 2
b1 4
1!
#30
0!
#35
b1 %
b1 9
b10 ,
b10 6
b10010010 (
b10010010 3
b1 +
b1 /
b1 7
b10 &
b10 2
b10 4
1!
#40
0!
#45
b10 $
b10 1
b10 :
b10 %
b10 9
b0 '
b0 .
b1 ,
b1 6
b100000001 (
b100000001 3
b11 &
b11 2
b11 4
1!
#50
0!
#55
b1 $
b1 1
b1 :
b0 %
b0 9
b1 '
b1 .
b10001 (
b10001 3
b100 &
b100 2
b100 4
1!
#60
0!
#65
b10 $
b10 1
b10 :
b1 %
b1 9
b10 -
b10 0
b10 5
b10 ,
b10 6
b10010010 (
b10010010 3
b101 &
b101 2
b101 4
1!
#70
0!
#75
b11 $
b11 1
b11 :
b10 %
b10 9
b0 '
b0 .
b1 ,
b1 6
b100000001 (
b100000001 3
b110 &
b110 2
b110 4
1!
#80
0!
#85
b10 $
b10 1
b10 :
b0 %
b0 9
b1 '
b1 .
b10001 (
b10001 3
b111 &
b111 2
b111 4
1!
#90
0!
#95
b11 $
b11 1
b11 :
b1 %
b1 9
b11 -
b11 0
b11 5
b10 ,
b10 6
b10010010 (
b10010010 3
b10 +
b10 /
b10 7
b1000 &
b1000 2
b1000 4
1!
#100
0!
#105
b101 $
b101 1
b101 :
b10 %
b10 9
b0 '
b0 .
b1 ,
b1 6
b100000001 (
b100000001 3
b1001 &
b1001 2
b1001 4
1!
#110
0!
#115
b11 $
b11 1
b11 :
b0 %
b0 9
b1 '
b1 .
b10001 (
b10001 3
b1010 &
b1010 2
b1010 4
1!
#120
0!
#125
b101 $
b101 1
b101 :
b1 %
b1 9
b101 -
b101 0
b101 5
b10 ,
b10 6
b10010010 (
b10010010 3
b1011 &
b1011 2
b1011 4
b11 +
b11 /
b11 7
1!
#130
0!
#135
b1000 $
b1000 1
b1000 :
b10 %
b10 9
b0 '
b0 .
b1 ,
b1 6
b100000001 (
b100000001 3
b1100 &
b1100 2
b1100 4
1!
#140
0!
#145
b101 $
b101 1
b101 :
b0 %
b0 9
b1 '
b1 .
b10001 (
b10001 3
b1101 &
b1101 2
b1101 4
1!
#150
0!
#155
b1000 $
b1000 1
b1000 :
b1 %
b1 9
b1000 -
b1000 0
b1000 5
b10 ,
b10 6
b10010010 (
b10010010 3
b101 +
b101 /
b101 7
b1110 &
b1110 2
b1110 4
1!
#160
0!
#165
b1101 $
b1101 1
b1101 :
b10 %
b10 9
b0 '
b0 .
b1 ,
b1 6
b100000001 (
b100000001 3
b1111 &
b1111 2
b1111 4
1!
#170
0!
#175
b1000 $
b1000 1
b1000 :
b0 %
b0 9
b1 '
b1 .
b10001 (
b10001 3
b10000 &
b10000 2
b10000 4
1!
#180
0!
#185
b1101 $
b1101 1
b1101 :
b1 %
b1 9
b1101 -
b1101 0
b1101 5
b10 ,
b10 6
b10010010 (
b10010010 3
b10001 &
b10001 2
b10001 4
b1000 +
b1000 /
b1000 7
1!
#190
0!
#195
b10101 $
b10101 1
b10101 :
b10 %
b10 9
b0 '
b0 .
b1 ,
b1 6
b100000001 (
b100000001 3
b10010 &
b10010 2
b10010 4
1!
#200
0!
#205
b1101 $
b1101 1
b1101 :
b0 %
b0 9
b1 '
b1 .
b10001 (
b10001 3
b10011 &
b10011 2
b10011 4
1!
#210
0!
#215
b10101 $
b10101 1
b10101 :
b1 %
b1 9
b10101 -
b10101 0
b10101 5
b10 ,
b10 6
b10010010 (
b10010010 3
b1101 +
b1101 /
b1101 7
b10100 &
b10100 2
b10100 4
1!
#220
0!
#225
0#
b11010 $
b11010 1
b11010 :
1)
b0 %
b0 9
b0 '
b0 .
b1101 -
b1101 0
b1101 5
b0 ,
b0 6
b1000000000 (
b1000000000 3
b10101 &
b10101 2
b10101 4
1!
